ili2c/__init__.py
ili2c/dataclasses/__init__.py
ili2c/dataclasses/generator.py
ili2c/dataclasses/ilismeta16.py
ili2c/dataclasses/examples/__init__.py
ili2c/dataclasses/examples/sqlalchemy_example.py
ili2c/dataclasses/examples/ui_scaffolding_example.py
ili2c/dataclasses/examples/data/SO_ARP_SEin_Konfiguration_20250115.ili
ili2c/dataclasses/examples/data/TestSuite_mod-0.ili
ili2c/dataclasses/examples/data/simple.ili
ili2c/ilirepository/__init__.py
ili2c/ilirepository/cache.py
ili2c/ilirepository/manager.py
ili2c/ilirepository/models.py
ili2c/ilirepository/repository.py
ili2c/pyili2c/__init__.py
ili2c/pyili2c/mermaid.py
ili2c/pyili2c/metamodel.py
ili2c/pyili2c/parser/__init__.py
ili2c/pyili2c/parser/core.py
ili2c/pyili2c/parser/generated/__init__.py
ili2c/pyili2c/parser/generated/grammars_antlr4/InterlisLexer.interp
ili2c/pyili2c/parser/generated/grammars_antlr4/InterlisLexer.py
ili2c/pyili2c/parser/generated/grammars_antlr4/InterlisLexer.tokens
ili2c/pyili2c/parser/generated/grammars_antlr4/InterlisParserPy.interp
ili2c/pyili2c/parser/generated/grammars_antlr4/InterlisParserPy.py
ili2c/pyili2c/parser/generated/grammars_antlr4/InterlisParserPy.tokens
ili2c/pyili2c/parser/generated/grammars_antlr4/InterlisParserPyListener.py
ili2c/pyili2c/parser/generated/grammars_antlr4/InterlisParserPyVisitor.py
ili2c/pyili2c/parser/generated/grammars_antlr4/__init__.py
ili2c_python-0.2.1.dist-info/METADATA
ili2c_python-0.2.1.dist-info/WHEEL
ili2c_python-0.2.1.dist-info/top_level.txt
ili2c_python-0.2.1.dist-info/RECORD
