Metadata-Version: 2.4
Name: ili2c-python
Version: 0.2.1
Summary: Python utilities for ili2c (INTERLIS metamodel, parser, and repository helpers).
Home-page: https://github.com/edigonzales/ili2c
Author: Stefan Ziegler
Author-email: stefan.ziegler.de@gmail.com
License: LGPL-2.1-or-later
Requires-Python: >=3.10
Requires-Dist: antlr4-python3-runtime<4.14,>=4.13
Provides-Extra: test
Requires-Dist: pytest>=8.0; extra == "test"
Provides-Extra: examples
Requires-Dist: sqlalchemy<3.0,>=2.0; extra == "examples"
